{
    "SP_SrSurveylanceIpAddress": {
        "id": "SP_SrSurveylanceIpAddress",
        "type": "A",
        "name": "P\u0159id\u011blen\u00ed dohl. IP, port\u016f pro v\u00fdstavbu",
        "urgent": false,
        "taskId": "TT_Automat",
        "workplaceId": "WP_System",
        "setupActionId": "undefined",
        "syncType": "NONE",
        "term": "",
        "termType": "day",
        "params": "",
        "autofinishMessage": "",
        "autoWorkOutAfterTerm": false,
        "generateCancelOnGlobalCancel": false,
        "top": "129",
        "left": "59"
    }
}