{
    "SP_SrCheckAvailability": {
        "id": "SP_SrCheckAvailability",
        "type": "A",
        "name": "Pr\u016fzkum",
        "urgent": false,
        "taskId": "TT_Automat",
        "workplaceId": "WP_System",
        "setupActionId": "undefined",
        "syncType": "NONE",
        "term": "5",
        "termType": "work_day",
        "params": "",
        "autofinishMessage": "",
        "autoWorkOutAfterTerm": false,
        "generateCancelOnGlobalCancel": false,
        "top": "97",
        "left": "39"
    }
}