{
    "TA_SrIpAddressAllocation": {
        "id": "TA_SrIpAddressAllocation",
        "type": "M",
        "name": "P\u0159id\u011blen\u00ed IP adres",
        "canMerge": false,
        "taskId": "TT_SrIpAddressAllocation",
        "workplaceId": "WP_ConfigurationData",
        "setupActionId": "undefined",
        "syncType": "FULL",
        "term": "",
        "termType": "day",
        "nestedWorkflow": {
            "0": ""
        },
        "canRedo": false,
        "sendEmail": false,
        "urgent": false,
        "outOfWorkFlow": false,
        "params": "",
        "autofinishMessage": "",
        "autoWorkOutAfterTerm": false,
        "generateCancelOnGlobalCancel": false,
        "top": "162",
        "left": "286"
    }
}